echo21/__init__.py
echo21/const.py
echo21/echofuncs.py
echo21/echopipeline.py
echo21/misc.py
echo21/setup.py
echo21-2.0.1.dist-info/METADATA
echo21-2.0.1.dist-info/WHEEL
echo21-2.0.1.dist-info/licenses/LICENSE
echo21-2.0.1.dist-info/RECORD
