Metadata-Version: 2.4
Name: echo21
Version: 2.0.1
Summary: Exploring the Cosmos with Hydrogen Observation
Project-URL: Repository, https://github.com/shikharmittal04/echo21.git
Author-email: Shikhar Mittal <shikhar.mittal4@gmail.com>
License: MIT License
License-File: LICENSE
Keywords: 21-cm,cosmology,global signal
Classifier: License :: OSI Approved :: MIT License
Classifier: Natural Language :: English
Classifier: Operating System :: OS Independent
Classifier: Programming Language :: Python :: 3.8
Classifier: Programming Language :: Python :: 3.9
Classifier: Programming Language :: Python :: 3.10
Classifier: Topic :: Scientific/Engineering :: Astronomy
Requires-Python: >=3.8
Requires-Dist: colossus
Requires-Dist: mpi4py
Requires-Dist: pybaselines
